{
  "done": true,
  "migration": {
    "name": "mig_cs81m0qaummr4an38dhg",
    "operations": [
      {
        "add_column": {
          "table": "Comments",
          "column": {
            "pk": false,
            "name": "userId",
            "type": "text",
            "unique": false,
            "comment": "{\"xata.link\":\"Users\"}",
            "nullable": true,
            "references": {
              "name": "userId_link",
              "table": "Users",
              "column": "xata_id",
              "on_delete": "SET NULL"
            }
          }
        }
      }
    ]
  },
  "migrationType": "pgroll",
  "name": "mig_cs81m0qaummr4an38dhg",
  "parent": "mig_cs81l2iaummr4an38dfg",
  "schema": "public",
  "startedAt": "2024-10-16T19:59:00.520491Z"
}
